edgy_lines/Edge2.py
edgy_lines/__init__.py
edgy_lines-0.0.1.dist-info/LICENSE
edgy_lines-0.0.1.dist-info/METADATA
edgy_lines-0.0.1.dist-info/WHEEL
edgy_lines-0.0.1.dist-info/top_level.txt
edgy_lines-0.0.1.dist-info/RECORD
