Metadata-Version: 2.1
Name: edgy-lines
Version: 0.0.1
Summary: A package for processing edges and lines
Home-page: https://github.com/ES-Alexander/edgy-lines
Author: ES-Alexander
License: UNKNOWN
Platform: UNKNOWN
Classifier: Programming Language :: Python :: 3
Classifier: License :: OSI Approved :: MIT License
Classifier: Operating System :: OS Independent
Requires-Python: >=3.6
Requires-Dist: numpy
